pywordpress.py
setup.py
pywordpress.egg-info/PKG-INFO
pywordpress.egg-info/SOURCES.txt
pywordpress.egg-info/dependency_links.txt
pywordpress.egg-info/not-zip-safe
pywordpress.egg-info/top_level.txt