Metadata-Version: 1.0
Name: pywordpress
Version: 0.1
Summary: A pythonic interface to Wordpress using the Wordpress XML-RPC API
Home-page: http://bitbucket.org/rgrp/pywordpress/
Author: Rufus Pollock
Author-email: UNKNOWN
License: mit
Keywords: wordpress python
Platform: UNKNOWN
Classifier: Development Status :: 5 - Production/Stable
Classifier: Environment :: Console
Classifier: Intended Audience :: Developers
Classifier: License :: OSI Approved :: BSD License
Classifier: Operating System :: OS Independent
Classifier: Programming Language :: Python
Classifier: Topic :: Software Development :: Libraries :: Python Modules
